named_semaphores/__init__.py
named_semaphores/logging.py
named_semaphores/py.typed
named_semaphores/semaphore.py
named_semaphores-1.0.3.dist-info/METADATA
named_semaphores-1.0.3.dist-info/WHEEL
named_semaphores-1.0.3.dist-info/licenses/LICENSE
named_semaphores-1.0.3.dist-info/RECORD
