Metadata-Version: 2.3
Name: named_semaphores
Version: 1.0.3
Summary: High-level POSIX IPC named semaphores for Python
Project-URL: Repository, https://github.com/johacks/named-semaphores
Project-URL: Issues, https://github.com/johacks/named-semaphores/issues
Author-email: johacks <joaquinjimenezlc@gmail.com>
Maintainer-email: johacks <joaquinjimenezlc@gmail.com>
Keywords: concurrency,inter-process communication,ipc,named-semaphore,named-semaphores,posix,posix-ipc,semaphore,semaphores,synchronization,threading
Classifier: Development Status :: 5 - Production/Stable
Classifier: Intended Audience :: Developers
Classifier: License :: OSI Approved :: Apache Software License
Classifier: Operating System :: POSIX
Classifier: Programming Language :: Python :: 3
Classifier: Programming Language :: Python :: 3.8
Classifier: Programming Language :: Python :: 3.9
Classifier: Programming Language :: Python :: 3.10
Classifier: Programming Language :: Python :: 3.11
Classifier: Programming Language :: Python :: 3.12
Classifier: Programming Language :: Python :: 3.13
Classifier: Topic :: Software Development :: Libraries
Classifier: Topic :: Software Development :: Libraries :: Python Modules
Classifier: Topic :: Utilities
Classifier: Typing :: Typed
Requires-Python: >=3.8
Requires-Dist: posix-ipc>=1.0.0
Requires-Dist: typing-extensions>=4.12.2
